pylocus/__init__.py
pylocus/algorithms.py
pylocus/basics.py
pylocus/basics_angles.py
pylocus/distributed_mds.py
pylocus/edm_completion.py
pylocus/lateration.py
pylocus/mds.py
pylocus/opt_space.py
pylocus/plots_cti.py
pylocus/point_set.py
pylocus/settings.py
pylocus/simulation.py
pylocus-0.0.5.dist-info/LICENSE
pylocus-0.0.5.dist-info/METADATA
pylocus-0.0.5.dist-info/WHEEL
pylocus-0.0.5.dist-info/top_level.txt
pylocus-0.0.5.dist-info/RECORD
